[
  {
    "Concepte": "Gossos Recollits",
    "Gener": 46,
    "Febrer": 33,
    "Març": 55,
    "Abril": 54,
    "Maig": 61,
    "Juny": 66,
    "Juliol": 56,
    "Agost": 49,
    "Setembre": 74,
    "Octubre": 93,
    "Novembre": 57,
    "Desembre": 68
  },
  {
    "Concepte": "Gossos Rescatats",
    "Gener": 18,
    "Febrer": 20,
    "Març": 14,
    "Abril": 22,
    "Maig": 19,
    "Juny": 21,
    "Juliol": 26,
    "Agost": 19,
    "Setembre": 25,
    "Octubre": 17,
    "Novembre": 22,
    "Desembre": 19
  },
  {
    "Concepte": "Gossos Adoptats",
    "Gener": 27,
    "Febrer": 49,
    "Març": 26,
    "Abril": 23,
    "Maig": 25,
    "Juny": 14,
    "Juliol": 18,
    "Agost": 14,
    "Setembre": 31,
    "Octubre": 29,
    "Novembre": 33,
    "Desembre": 36
  },
  {
    "Concepte": "Gats Recollits",
    "Gener": 30,
    "Febrer": 31,
    "Març": 27,
    "Abril": 35,
    "Maig": 100,
    "Juny": 96,
    "Juliol": 85,
    "Agost": 62,
    "Setembre": 62,
    "Octubre": 73,
    "Novembre": 40,
    "Desembre": 32
  },
  {
    "Concepte": "Gats Rescatats",
    "Gener": 6,
    "Febrer": 6,
    "Març": 2,
    "Abril": 6,
    "Maig": 6,
    "Juny": 19,
    "Juliol": 16,
    "Agost": 19,
    "Setembre": 8,
    "Octubre": 11,
    "Novembre": 8,
    "Desembre": 7
  },
  {
    "Concepte": "Gats Adoptats",
    "Gener": 21,
    "Febrer": 46,
    "Març": 19,
    "Abril": 14,
    "Maig": 48,
    "Juny": 47,
    "Juliol": 32,
    "Agost": 47,
    "Setembre": 58,
    "Octubre": 28,
    "Novembre": 29,
    "Desembre": 27
  }
]